tabletools/__init__.py
tabletools/table_cat.py
tabletools/table_cut_columns.py
tabletools/table_group_summarize.py
tabletools/table_join.py
tabletools/table_paste_col.py
tabletools/table_to_excel.py
tabletools-1.0.2.dist-info/licenses/LICENSE
tests/__init__.py
tests/test_table_cat.py
tests/test_table_group_summarize.py
tests/test_table_join.py
tests/test_table_paste_col.py
tabletools-1.0.2.dist-info/METADATA
tabletools-1.0.2.dist-info/WHEEL
tabletools-1.0.2.dist-info/entry_points.txt
tabletools-1.0.2.dist-info/top_level.txt
tabletools-1.0.2.dist-info/RECORD
